stp/__init__.py
stp/info.py
stp/stochastic.py
stp/tests/__init__.py
stp/tools/gui.py
stp-0.0.1.5.dist-info/LICENSE
stp-0.0.1.5.dist-info/METADATA
stp-0.0.1.5.dist-info/WHEEL
stp-0.0.1.5.dist-info/RECORD
