Metadata-Version: 2.3
Name: stp
Version: 0.0.1.5
Summary: Stochastic Thermodynamics in Python
License: GNU GENERAL PUBLIC LICENSE
Keywords: stochastic,thermodynamics,python,information
Author: Jonathan Delgado
Author-email: jonathandelgado0327@gmail.com
Requires-Python: >=3.7
Classifier: Development Status :: 3 - Alpha
Classifier: Intended Audience :: Developers
Classifier: License :: Other/Proprietary License
Classifier: Operating System :: OS Independent
Classifier: Programming Language :: Python :: 3
Classifier: Programming Language :: Python :: 3.7
Classifier: Programming Language :: Python :: 3.8
Classifier: Programming Language :: Python :: 3.9
Classifier: Programming Language :: Python :: 3.10
Classifier: Programming Language :: Python :: 3.11
Classifier: Programming Language :: Python :: 3.12
Classifier: Programming Language :: Python :: 3.13
Project-URL: Homepage, https://jdelgado.net/
Project-URL: Repository, https://github.com/otanan/STP
